jupyter_anywidget_webllm/__init__.py
jupyter_anywidget_webllm/magics.py
jupyter_anywidget_webllm/panel.py
jupyter_anywidget_webllm/static/uuid.js
jupyter_anywidget_webllm/static/webllm.css
jupyter_anywidget_webllm/static/webllm.js
jupyter_anywidget_webllm/static/widget.css
jupyter_anywidget_webllm/static/widget.js
jupyter_anywidget_webllm-0.0.1.dist-info/METADATA
jupyter_anywidget_webllm-0.0.1.dist-info/WHEEL
jupyter_anywidget_webllm-0.0.1.dist-info/licenses/LICENSE
jupyter_anywidget_webllm-0.0.1.dist-info/RECORD
