Metadata-Version: 2.3
Name: jupyter_anywidget_webllm
Version: 0.0.1
Summary: Jupyter anywidget for sideloading webllm wasm
Author-email: Tony Hirst <tony.hirst@gmail.com>
Requires-Dist: anywidget
Provides-Extra: dev
Requires-Dist: jupyterlab; extra == 'dev'
Requires-Dist: watchfiles; extra == 'dev'
